{"trial_id": "bf2fb788a1787ffd32b2ab0241f59884", "hyperparameters": {"space": [{"class_name": "Float", "config": {"name": "regularizers_2", "default": 0.01, "conditions": [], "min_value": 1e-08, "max_value": 1.0, "step": null, "sampling": "log"}}, {"class_name": "Float", "config": {"name": "regularizers_1", "default": 0.01, "conditions": [], "min_value": 1e-08, "max_value": 0.15, "step": null, "sampling": "log"}}, {"class_name": "Choice", "config": {"name": "dense_activation", "default": "selu", "conditions": [], "values": ["relu", "selu", "elu"], "ordered": false}}, {"class_name": "Choice", "config": {"name": "units_0", "default": 96, "conditions": [], "values": [64, 96, 128, 160, 192], "ordered": true}}, {"class_name": "Choice", "config": {"name": "units_1", "default": 64, "conditions": [], "values": [64, 96, 128], "ordered": true}}, {"class_name": "Choice", "config": {"name": "units_2", "default": 64, "conditions": [], "values": [48, 64, 96], "ordered": true}}, {"class_name": "Float", "config": {"name": "dropout_1", "default": 0.25, "conditions": [], "min_value": 0.0, "max_value": 0.5, "step": 0.05, "sampling": null}}, {"class_name": "Float", "config": {"name": "learning_rate", "default": 0.001, "conditions": [], "min_value": 0.0001, "max_value": 0.01, "step": null, "sampling": "log"}}, {"class_name": "Choice", "config": {"name": "batch_size", "default": 64, "conditions": [], "values": [32, 64, 128, 256], "ordered": true}}], "values": {"regularizers_2": 0.001307895336033816, "regularizers_1": 5.679954497271543e-07, "dense_activation": "elu", "units_0": 192, "units_1": 128, "units_2": 96, "dropout_1": 0.15000000000000002, "learning_rate": 0.0010504922010059405, "batch_size": 128, "tuner/epochs": 15, "tuner/initial_epoch": 4, "tuner/bracket": 1, "tuner/round": 1, "tuner/trial_id": "c4bf878edc35f9c38477fd9df7e88f4b"}}, "metrics": {"metrics": {"loss": {"direction": "min", "observations": [{"value": [2.08947491645813], "step": 0}]}, "mae": {"direction": "min", "observations": [{"value": [1.8455623388290405], "step": 0}]}, "val_loss": {"direction": "min", "observations": [{"value": [2.004836320877075], "step": 0}]}, "val_mae": {"direction": "min", "observations": [{"value": [1.7569493055343628], "step": 0}]}}}, "score": 1.7569493055343628, "best_step": 0, "status": "COMPLETED"}